{
  "status": "ok",
  "data": {
    "timestamp": "2026-04-30T23:10:46+08:00",
    "location": "Shenzhen, China",
    "t0": {
      "prediction": "low_freq_rumble",
      "rms_ratio": 5.91,
      "zero_crossing_rate": 1586.0,
      "weather_prior": "overcast",
      "image_size_kb": 39.6
    },
    "t2_poem": "A soft hush descends upon the city as the sky whispers hues of dawn or dusk, a gentle rhythm of footsteps echoing in the quiet expanse.",
    "autocatalytic_index": 3.376,
    "disagreements": 0,
    "mode": "full",
    "corrections_count": 0,
    "patterns_count": 0,
    "total_cycles": 15,
    "human_voice": {
      "moment": "听，深圳在低声说话。",
      "soundscape": "窗外一直有那种很低沉的嗡嗡声，像城市在打呼噜，不是车流声，闷闷的。现在快十一点了，感觉整栋楼都在跟着哼。",
      "letter_to_future": "现在是深夜十一点十分，窗外有持续的低沉嗡鸣，像城市在深呼吸。天阴着，没有星星。记住这个声音，它告诉你——即使最安静的夜晚，深圳也没有真正睡去。你也不是一个人醒着。"
    }
  }
}